mnnai/Generator.py
mnnai/__init__.py
mnnai/Text_to_image/Image.py
mnnai/Text_to_image/__init__.py
mnnai/Text_to_text/Text.py
mnnai/Text_to_text/__init__.py
mnnlibr-3.0.0.dist-info/LICENSE
mnnlibr-3.0.0.dist-info/METADATA
mnnlibr-3.0.0.dist-info/WHEEL
mnnlibr-3.0.0.dist-info/top_level.txt
mnnlibr-3.0.0.dist-info/RECORD
