Metadata-Version: 2.1
Name: mnnlibr
Version: 3.0.0
Summary: Module for using AI
Home-page: https://github.com/mkshustov/MNNLibr
Author: mkshustov
Author-email: mkshustov@mail.ru
Project-URL: Documentation, https://github.com/mkshustov/MNNLibr
Keywords: ai MNN chatgpt
Classifier: Programming Language :: Python :: 3.11
Classifier: License :: OSI Approved :: MIT License
Classifier: Operating System :: OS Independent
Requires-Python: >=3.7
License-File: LICENSE
Requires-Dist: requests >=2.25.1
Requires-Dist: aiohttp
